iv/__init__.py
iv-1.0.5.dist-info/METADATA
iv-1.0.5.dist-info/WHEEL
iv-1.0.5.dist-info/entry_points.txt
iv-1.0.5.dist-info/top_level.txt
iv-1.0.5.dist-info/RECORD
