Metadata-Version: 2.1
Name: iv
Version: 1.0.5
Summary: Flexible terminal image viewer for iTerm2
Home-page: https://github.com/russss/iv
Author: Russ Garrett
Author-email: russ@garrett.co.uk
License: MIT
Keywords: image iterm2 cli terminal
Platform: UNKNOWN
Classifier: Development Status :: 4 - Beta
Classifier: License :: OSI Approved :: MIT License
Classifier: Programming Language :: Python :: 3
Requires-Python: >=3.4
Requires-Dist: pillow (>=6)
Requires-Dist: imgcat
Requires-Dist: click (>=7)
